cocotb_kernel/__init__.py
cocotb_kernel/__main__.py
cocotb_kernel/install.py
cocotb_kernel/module.py
cocotb_kernel-2.0.1.dist-info/licenses/LICENSE
cocotb_kernel-2.0.1.dist-info/WHEEL
cocotb_kernel-2.0.1.dist-info/METADATA
cocotb_kernel-2.0.1.dist-info/RECORD
