Metadata-Version: 2.4
Name: cocotb_kernel
Version: 2.0.1
Summary: Jupyter kernel for cocotb
Author-email: Matthew Michilot <matthew.michilot@gmail.com>
Requires-Python: >=3.11,<3.14
Classifier: License :: OSI Approved :: MIT License
Classifier: Programming Language :: Python :: 3.11
Classifier: Framework :: cocotb
Classifier: Framework :: Jupyter
Classifier: Topic :: Scientific/Engineering :: Electronic Design Automation (EDA)
License-File: LICENSE
Requires-Dist: cocotb>=2
Requires-Dist: ruff ~= 0.5.0 ; extra == "lint"
Requires-Dist: mypy ~= 1.10.0 ; extra == "lint"
Project-URL: Source, https://github.com/mmichilot/cocotb_kernel
Provides-Extra: lint
